{
  "/_not-found/page": "app/_not-found/page.js",
  "/api/graphql/route": "app/api/graphql/route.js",
  "/api/auth/login/route": "app/api/auth/login/route.js",
  "/login/page": "app/login/page.js",
  "/(dashboard)/admin/branches/page": "app/(dashboard)/admin/branches/page.js",
  "/(dashboard)/admin/settings/page": "app/(dashboard)/admin/settings/page.js",
  "/(dashboard)/admin/users/page": "app/(dashboard)/admin/users/page.js",
  "/(dashboard)/admin/page": "app/(dashboard)/admin/page.js",
  "/(dashboard)/automobile/page": "app/(dashboard)/automobile/page.js",
  "/(dashboard)/automobile/settings/page": "app/(dashboard)/automobile/settings/page.js",
  "/(dashboard)/automobile/vehicles/page": "app/(dashboard)/automobile/vehicles/page.js",
  "/(dashboard)/repair/appointments/page": "app/(dashboard)/repair/appointments/page.js",
  "/(dashboard)/automobile/vehicles/[id]/page": "app/(dashboard)/automobile/vehicles/[id]/page.js",
  "/(dashboard)/repair/customers/page": "app/(dashboard)/repair/customers/page.js",
  "/(dashboard)/repair/page": "app/(dashboard)/repair/page.js",
  "/(dashboard)/repair/invoices/page": "app/(dashboard)/repair/invoices/page.js",
  "/(dashboard)/repair/settings/page": "app/(dashboard)/repair/settings/page.js",
  "/(dashboard)/repair/staff/[id]/page": "app/(dashboard)/repair/staff/[id]/page.js",
  "/(dashboard)/repair/staff/page": "app/(dashboard)/repair/staff/page.js",
  "/(dashboard)/automobile/staff/page": "app/(dashboard)/automobile/staff/page.js",
  "/(dashboard)/store/page": "app/(dashboard)/store/page.js",
  "/(dashboard)/repair/vehicles/page": "app/(dashboard)/repair/vehicles/page.js",
  "/(dashboard)/store/products/page": "app/(dashboard)/store/products/page.js",
  "/(dashboard)/store/purchase-orders/page": "app/(dashboard)/store/purchase-orders/page.js",
  "/(dashboard)/store/settings/page": "app/(dashboard)/store/settings/page.js",
  "/(dashboard)/store/suppliers/page": "app/(dashboard)/store/suppliers/page.js",
  "/(dashboard)/automobile/staff/[id]/page": "app/(dashboard)/automobile/staff/[id]/page.js",
  "/(dashboard)/store/inventory/page": "app/(dashboard)/store/inventory/page.js"
}